{
  "versions": [
    {
	  "version": "aov-2019.1",
	  "prev": "aov-2018.12",
	  "update": [
	    {
		  "action": "delete",
		  "targets": [
		    "base/characters/Margaret/[PRE]-damage.gif",
			"base/characters/Margaret/[PRE]-Burst.gif",
			"base/characters/Margaret/[PRE]-enough.gif",
			"base/characters/Margaret/[PRE]-intro.gif",
			"base/characters/Margaret/[PRE]-objection.gif",
			"base/characters/Margaret/[PRE]-oof.gif",
			"base/characters/Margaret/[PRE]-Peace.gif",
			"base/characters/Margaret/[PRE]-present.gif",
			"base/characters/Margaret/[PRE]-shock.gif",
			"base/characters/Margaret/[PRE]-show.gif",
			"base/characters/Margaret/[PRE]-slam.gif",
			"base/characters/Margaret/[PRE]-slamX2.gif",
			"base/characters/Margaret/[PRE]-slip.gif",
			"base/characters/Margaret/[PRE]-swipe.gif",
			"base/sounds/music/[AOV] anime.mp3",
			"base/sounds/music/[DGS] Detention Center.mp3",
			"base/sounds/music/[DGS] Joint Reasoning (Type B-2).mp3",
			"base/sounds/music/[DGS] Reasoning Battle.mp3",
			"base/sounds/music/[DGS] Reasoning Battle (Allegro).mp3",
			"base/sounds/music/[DGS] The Musings of Sherlock Holmes.mp3"
		  ]
		},
		{
		  "action": "deleteDir",
		  "targets": [
		    "base/characters/Justine CourtneyPro"
		  ]
		},
		{
		  "action": "dl",
		  "url": "https://s3.wasabisys.com/aov/And_A_Happy_New_Update.zip",
		  "hash": "2988c0f2c1e6bfb3aa2cd7a77c432d60ee8c826c"
		}
	  ]
	},
	{
	  "version": "aov-2018.12",
	  "prev": "aov-2018.11",
	  "update": [
		{
		  "action": "deleteDir",
		  "targets": [
		    "base/characters/Rise",
			"base/characters/Justine Courtney"
		  ]
		},
		{
		  "action": "dl",
		  "url": "https://s3.wasabisys.com/aov/Holly_Jolly_Update.zip",
		  "hash": "b3149d46615ad1af8372d3ed6aaacdedde1e2021"
		}
	  ]
	},
	{
      "version": "aov-2018.11",
      "full": [
        {
          "action": "dl",
          "url": "https://s3.wasabisys.com/aov/Full_Characters_1.zip"
        },
        {
          "action": "dl",
          "url": "https://s3.wasabisys.com/aov/Full_Characters_2.zip",
          "hash": "9feceb9ad09cd403941584e43df42015e4a72139"
        },
        {
          "action": "dl",
          "url": "https://s3.wasabisys.com/aov/Full_Music.zip",
          "hash": "8b23c0dc46562caee4f0474b731fdd7507095a4a"
        },
		{
		  "action": "dl",
		  "url": "https://s3.wasabisys.com/aov/Full_Misc.zip",
		  "hash": "fc71bda28cf40531aeea8882e77a9e75253175f0"
		}
      ]
    }
  ]
}